youtube_scraping_api/__init__.py
youtube_scraping_api/__main__.py
youtube_scraping_api/caption.py
youtube_scraping_api/cipher.py
youtube_scraping_api/constants.py
youtube_scraping_api/decorators.py
youtube_scraping_api/filter.py
youtube_scraping_api/urls.py
youtube_scraping_api/utils.py
youtube_scraping_api/parser/__init__.py
youtube_scraping_api/parser/channel.py
youtube_scraping_api/parser/playlist.py
youtube_scraping_api/parser/search_result.py
youtube_scraping_api/parser/video.py
youtube_scraping_api-1.1.3.dist-info/LICENSE
youtube_scraping_api-1.1.3.dist-info/METADATA
youtube_scraping_api-1.1.3.dist-info/WHEEL
youtube_scraping_api-1.1.3.dist-info/top_level.txt
youtube_scraping_api-1.1.3.dist-info/RECORD
