Metadata-Version: 2.1
Name: youtube-scraping-api
Version: 1.1.3
Summary: A scraper for everything on YouTube
Home-page: https://github.com/melvinchia3636/YouTube-Scraping-API
Author: The Silly Coder
Author-email: melvinchia623600@gmail.com
License: UNKNOWN
Project-URL: Bug Tracker, https://github.com/melvinchia3636/YouTube-Scraping-API/issues
Platform: UNKNOWN
Classifier: Programming Language :: Python :: 3.8
Classifier: Programming Language :: Python :: 3.9
Classifier: Natural Language :: English
Classifier: License :: OSI Approved :: MIT License
Classifier: Operating System :: OS Independent
Classifier: Programming Language :: Python
Classifier: Topic :: Internet
Classifier: Topic :: Multimedia :: Video
Classifier: Topic :: Software Development :: Libraries :: Python Modules
Requires-Python: >=3.8
License-File: LICENSE
